cyril/__init__.py
cyril/__main__.py
cyril/commands/__init__.py
cyril/commands/ask.py
cyril/commands/bash.py
cyril/commands/keyboard.py
cyril/commands/register.py
cyril/commands/terraform.py
cyril/config.py
cyril/load_env/__init__.py
cyril/load_env/load.py
cyril/operators/__init__.py
cyril/operators/abc.py
cyril/operators/gemini.py
cyril/operators/gemini_API.py
cyril/operators/open_ai.py
cyril/scripts/format.sh
cyril/scripts/lint.sh
cyril/scripts/test.sh
cyril1-0.1.5.dist-info/METADATA
cyril1-0.1.5.dist-info/WHEEL
cyril1-0.1.5.dist-info/entry_points.txt
cyril1-0.1.5.dist-info/RECORD
