Metadata-Version: 2.1
Name: cyril1
Version: 0.1.5
Summary: 
Home-page: https://github.com/RaphOb/Cyril
Author: Raphael Obadia
Author-email: o.raphou@gmail.com
Requires-Python: >=3.9
Classifier: License :: OSI Approved :: MIT License
Classifier: Programming Language :: Python :: 3
Classifier: Programming Language :: Python :: 3.9
Classifier: Programming Language :: Python :: 3.10
Classifier: Programming Language :: Python :: 3.11
Classifier: Topic :: Software Development :: Build Tools
Requires-Dist: black (>=24.3.0,<25.0.0)
Requires-Dist: google-auth (>=2.29.0,<3.0.0)
Requires-Dist: google-generativeai (>=0.5.0,<0.6.0)
Requires-Dist: halo (>=0.0.31,<0.0.32)
Requires-Dist: httpx (>=0.27.0,<0.28.0)
Requires-Dist: openai (>=1.16.2,<2.0.0)
Requires-Dist: pydantic-settings (>=2.2.1,<3.0.0)
Requires-Dist: requests (>=2.31.0,<3.0.0)
Requires-Dist: ruff (>=0.3.5,<0.4.0)
Requires-Dist: typer (>=0.12.1,<0.13.0)
Project-URL: Repository, https://github.com/RaphOb/Cyril
